updatereqspec/__init__.py
updatereqspec/cli.py
updatereqspec/config.py
updatereqspec/exceptions.py
updatereqspec/latest_version_finder.py
updatereqspec/requirement_updater.py
updatereqspec/source_replacer.py
updatereqspec/update.py
update_req_spec-1.0.2.dist-info/LICENSE
update_req_spec-1.0.2.dist-info/METADATA
update_req_spec-1.0.2.dist-info/WHEEL
update_req_spec-1.0.2.dist-info/entry_points.txt
update_req_spec-1.0.2.dist-info/top_level.txt
update_req_spec-1.0.2.dist-info/RECORD
