Metadata-Version: 2.1
Name: update-req-spec
Version: 1.0.2
Summary: Update Python requirements in a setup.py file to permit latest available versions
Home-page: https://github.com/RobbieClarken/update-req-spec
Author: Robbie Clarken
Author-email: robert.clarken@reece.com.au
License: MIT
Platform: UNKNOWN
Classifier: Development Status :: 5 - Production/Stable
Classifier: Intended Audience :: Developers
Classifier: Intended Audience :: Developers
Classifier: License :: OSI Approved :: MIT License
Classifier: Programming Language :: Python :: 3
Classifier: Programming Language :: Python :: 3.6
Classifier: Programming Language :: Python :: Implementation :: CPython
Classifier: Topic :: Software Development :: Libraries
Classifier: Topic :: Utilities
Requires-Dist: click
Requires-Dist: pip-tools
